{
  "@context": "https://schema.org",
  "@type": "FAQPage",
  "name": "Do I need a lawyer for my warehouse forklift injury workers' comp in Ogden?",
  "description": "Yes if denied or valuable; contingency fee.[1]",
  "url": "https://justworkcomplaw.com//faq/general-do-i-need-a-lawyer-for-my-warehouse-forklift-injury-workers-comp-in-ogden-307",
  "mainEntity": [
    {
      "@type": "Question",
      "name": "Do I need a lawyer for my warehouse forklift injury workers' comp in Ogden?",
      "acceptedAnswer": {
        "@type": "Answer",
        "text": "Yes if denied or valuable; contingency fee.[1]",
        "description": "**Not always for simple claims, but yes if denied, complex, or third-party involved - they boost settlements 2-3x.** Fees are 20% contingency from benefits.[1] Key factors: insurers lowball without counsel; free consults available. Handle paperwork yourself initially, but lawyer up if stalled. Higher payouts justify it.[10]"
      }
    }
  ]
}