{
  "@context": "https://schema.org",
  "@type": "FAQPage",
  "name": "How much does a workers comp lawyer cost for occupational illness in Boise?",
  "description": "20% contingency, free upfront[4].",
  "url": "https://justworkcomplaw.com//faq/occupational-illness-how-much-does-a-workers-comp-lawyer-cost-for-occupational-illness-in-boise-244",
  "mainEntity": [
    {
      "@type": "Question",
      "name": "How much does a workers comp lawyer cost for occupational illness in Boise?",
      "acceptedAnswer": {
        "@type": "Answer",
        "text": "20% contingency, free upfront[4].",
        "description": "Usually 20% contingency of benefits, no win no fee.\n\nNo upfront costs; ethical caps apply[4].\n\n- Recover fees from insurer.\n- Free consults standard.\n- Higher settlements offset.\n\nShop experienced locals."
      }
    }
  ]
}